yog_sothoth/__init__.py
yog_sothoth/go.mod
yog_sothoth/main.go
yog_sothoth-0.0.1.dist-info/WHEEL
yog_sothoth-0.0.1.dist-info/entry_points.txt
yog_sothoth-0.0.1.dist-info/METADATA
yog_sothoth-0.0.1.dist-info/RECORD
