Metadata-Version: 2.3
Name: yog-sothoth
Version: 0.0.1
Summary: That one who knows all the secrets
Author: Fernando Bryan Reza Campos
Author-email: Fernando Bryan Reza Campos <fer.rezac@outlook.com>
Requires-Python: >=3.14
